app/__init__.py
app/agents/.agent.py.swp
app/agents/__init__.py
app/agents/agent.py
app/agents/callbacks.py
app/agents/custom_message.py
app/agents/direct_bedrock.py
app/agents/direct_streaming.py
app/agents/models.py
app/agents/parse_output.py
app/agents/prompts.py
app/agents/prompts_manager.py
app/agents/wrappers/__init__.py
app/agents/wrappers/google_direct.py
app/agents/wrappers/nova_formatter.py
app/agents/wrappers/nova_tool_execution.py
app/agents/wrappers/nova_wrapper.py
app/agents/wrappers/openai_bedrock_wrapper.py
app/agents/wrappers/ziya_bedrock.py
app/agents/wrappers/ziya_google_genai.py
app/api/chat_with_validation.py
app/api/formatters.py
app/cli.py
app/config/__init__.py
app/config/app_config.py
app/config/common_args.py
app/config/models_config.py
app/config/shell_config.py
app/extensions/__init__.py
app/extensions/post_instructions/README.md
app/extensions/post_instructions/__init__.py
app/extensions/post_instructions/gemini_post_instructions.py
app/extensions/post_instructions/sonnet_post_instructions.py
app/extensions/prompt_extensions/__init__.py
app/extensions/prompt_extensions/claude_extensions.py
app/extensions/prompt_extensions/cli_extensions.py
app/extensions/prompt_extensions/gemini_extensions.py
app/extensions/prompt_extensions/global_extensions.py
app/extensions/prompt_extensions/mcp_prompt_extensions.py
app/extensions/prompt_extensions/nova_extensions.py
app/main.py
app/mcp/__init__.py
app/mcp/builtin_tools.py
app/mcp/client.py
app/mcp/connection_pool.py
app/mcp/consolidated.py
app/mcp/cooldown.py
app/mcp/dynamic_tools.py
app/mcp/enhanced_tools.py
app/mcp/integration.py
app/mcp/manager.py
app/mcp/permissions.py
app/mcp/registry/INTEGRATION_GUIDE.md
app/mcp/registry/README.md
app/mcp/registry/__init__.py
app/mcp/registry/aggregator.py
app/mcp/registry/installation_helper.py
app/mcp/registry/interface.py
app/mcp/registry/providers/__init__.py
ziya-0.4.1.0.dist-info/METADATA
ziya-0.4.1.0.dist-info/RECORD
ziya-0.4.1.0.dist-info/RECORD
ziya-0.4.1.0.dist-info/WHEEL
ziya-0.4.1.0.dist-info/entry_points.txt
ziya-0.4.1.0.dist-info/licenses/LICENSE
