Metadata-Version: 2.4
Name: ziya
Version: 0.4.1.0
Summary: 
License: MIT
License-File: LICENSE
Author: Dan Cohn
Author-email: chroma@gmail.com
Requires-Python: >=3.10,<3.14
Classifier: License :: OSI Approved :: MIT License
Classifier: Programming Language :: Python :: 3
Classifier: Programming Language :: Python :: 3.10
Classifier: Programming Language :: Python :: 3.11
Classifier: Programming Language :: Python :: 3.12
Classifier: Programming Language :: Python :: 3.13
Provides-Extra: local
Requires-Dist: aiohttp (>=3.12.0,<4.0.0)
Requires-Dist: beautifulsoup4 (>=4.12.0,<5.0.0)
Requires-Dist: boto3 (>=1.35.0,<2.0.0)
Requires-Dist: cryptography (>=46.0.0,<47.0.0)
Requires-Dist: cssutils (>=2.11.0,<3.0.0)
Requires-Dist: fastapi (>=0.124.2,<0.125.0)
Requires-Dist: filelock (>=3.20.1)
Requires-Dist: fonttools (>=4.60.2,<5.0.0)
Requires-Dist: google-genai (>=1.7.0,<2.0.0)
Requires-Dist: html5lib (>=1.1,<2.0)
Requires-Dist: httpx (>=0.28.1,<0.29.0)
Requires-Dist: jinja2 (>=3.1.0,<4.0.0)
Requires-Dist: langchain (>=1.0.0,<2.0.0)
Requires-Dist: langchain-aws (>=1.1.0,<2.0.0)
Requires-Dist: langchain-classic (>=1.0.0,<2.0.0)
Requires-Dist: langchain-community (>=0.4.1,<0.5.0)
Requires-Dist: langchain-google-genai (>=2.0.0,<3.0.0)
Requires-Dist: langchain-text-splitters (>=1.0.0,<2.0.0)
Requires-Dist: langgraph (>=1.0.0,<2.0.0)
Requires-Dist: langgraph-prebuilt (>=1.0.0,<2.0.0)
Requires-Dist: langserve (>=0.3.0,<0.4.0)
Requires-Dist: mcp (>=1.23.0,<2.0.0)
Requires-Dist: openpyxl (>=3.1.0,<4.0.0)
Requires-Dist: packaging (>=24.0,<25.0)
Requires-Dist: pandas (>=2.2.0,<3.0.0)
Requires-Dist: pdfplumber (>=0.11.0,<0.12.0)
Requires-Dist: pillow (>=11.0.0,<12.0.0)
Requires-Dist: prompt-toolkit (>=3.0.48,<4.0.0)
Requires-Dist: pyOpenSSL (>=25.0.0,<26.0.0)
Requires-Dist: pydantic (>=2.10.0,<3.0.0)
Requires-Dist: pypdf (>=6.0.0,<7.0.0)
Requires-Dist: python-docx (>=1.1.0,<2.0.0)
Requires-Dist: python-pptx (>=1.0.0,<2.0.0)
Requires-Dist: requests (>=2.32.0,<3.0.0)
Requires-Dist: setuptools (>=75.8.0)
Requires-Dist: starlette (>=0.49.1)
Requires-Dist: torch (>=2.8.0,<3.0.0) ; extra == "local"
Requires-Dist: urllib3 (>=2.5.0,<3.0.0)
Requires-Dist: uv (>=0.9.6,<0.10.0)
Requires-Dist: uvicorn[standard] (>=0.38.0,<0.39.0)
Requires-Dist: watchdog (>=6.0.0,<7.0.0)
Requires-Dist: whatthepatch (>=1.0.6,<2.0.0)
